odoo8_addon_product_price_history-8.0.1.0.0.99.dev4-py3.8-nspkg.pth
odoo_addons/product_price_history/README.rst
odoo_addons/product_price_history/__init__.py
odoo_addons/product_price_history/__openerp__.py
odoo_addons/product_price_history/i18n/it.po
odoo_addons/product_price_history/i18n/product_price_history.pot
odoo_addons/product_price_history/models/__init__.py
odoo_addons/product_price_history/models/product_product.py
odoo_addons/product_price_history/models/product_template.py
odoo_addons/product_price_history/readme/CONTRIBUTORS.rst
odoo_addons/product_price_history/readme/DESCRIPTION.rst
odoo_addons/product_price_history/readme/HISTORY.rst
odoo_addons/product_price_history/readme/USAGE.rst
odoo_addons/product_price_history/static/description/icon.png
odoo_addons/product_price_history/static/description/index.html
odoo_addons/product_price_history/tests/__init__.py
odoo_addons/product_price_history/tests/test_product_price_history.py
odoo_addons/product_price_history/views/product_price_history_view.xml
odoo8_addon_product_price_history-8.0.1.0.0.99.dev4.dist-info/METADATA
odoo8_addon_product_price_history-8.0.1.0.0.99.dev4.dist-info/WHEEL
odoo8_addon_product_price_history-8.0.1.0.0.99.dev4.dist-info/namespace_packages.txt
odoo8_addon_product_price_history-8.0.1.0.0.99.dev4.dist-info/top_level.txt
odoo8_addon_product_price_history-8.0.1.0.0.99.dev4.dist-info/RECORD
