Metadata-Version: 2.1
Name: odoo8-addon-product-price-history
Version: 8.0.1.0.0.99.dev4
Summary: Handle standard price history records
Home-page: https://github.com/OCA/product-attribute
Author: Pordenone Linux User Group (PNLUG),Odoo Community Association (OCA)
Author-email: support@odoo-community.org
License: AGPL-3
Platform: UNKNOWN
Classifier: Programming Language :: Python
Classifier: Framework :: Odoo
Classifier: Framework :: Odoo :: 8.0
Classifier: License :: OSI Approved :: GNU Affero General Public License v3
Requires-Python: ~=2.7
Requires-Dist: odoo (<9.0a,>=8.0a)
